metaendpoints/__init__.py
metaendpoints/apimethod.py
metaendpoints/apiserver.py
metaendpoints/info.py
metaendpoints/tools/__init__.py
metaendpoints/tools/build_api_docs.py
metaendpoints/tools/build_docker_image.py
metaendpoints/tools/esp_deploy.py
metaendpoints/tools/esp_dev.py
metaendpoints/tools/esp_init.py
metaendpoints-0.7.0.dist-info/METADATA
metaendpoints-0.7.0.dist-info/WHEEL
metaendpoints-0.7.0.dist-info/top_level.txt
metaendpoints-0.7.0.dist-info/RECORD
