Metadata-Version: 2.1
Name: metaendpoints
Version: 0.7.0
Summary: Devision Meta Endpoints
Home-page: https://github.com/devision-io/metaendpoints
Author: Artur Geraschenko
Author-email: arturgspb@gmail.com
License: MIT
Classifier: Programming Language :: Python :: 3
Requires-Dist: grpcio (==1.47.0)
Requires-Dist: gcloud (==0.18.3)
Requires-Dist: google-api-python-client (==1.7.3)
Requires-Dist: grpcio-health-checking (==1.27.2)
Requires-Dist: docker (==2.5.1)
Requires-Dist: metasdk (~=1.5.0)
Requires-Dist: pyyaml
